grayskull/__init__.py
grayskull/__main__.py
grayskull/_version.py
grayskull/config.py
grayskull/main.py
grayskull/utils.py
grayskull/base/__init__.py
grayskull/base/factory.py
grayskull/base/github.py
grayskull/base/pkg_info.py
grayskull/base/track_packages.py
grayskull/cli/__init__.py
grayskull/cli/parser.py
grayskull/cli/stdout.py
grayskull/license/__init__.py
grayskull/license/discovery.py
grayskull/license/licence_cache.json
grayskull/license/data/AGPL-3.0-only
grayskull/license/data/Apache-2.0
grayskull/license/data/BSD-2-Clause
grayskull/license/data/BSD-3-Clause
grayskull/license/data/BSD-4-Clause
grayskull/license/data/CC0-1.0
grayskull/license/data/EPL-2.0
grayskull/license/data/GPL-2.0-only
grayskull/license/data/GPL-3.0-only
grayskull/license/data/LGPL-2.1-only
grayskull/license/data/LGPL-3.0-only
grayskull/license/data/MIT
grayskull/license/data/MPL-2.0
grayskull/license/data/Unlicense
grayskull/license/data/__init__.py
grayskull/strategy/__init__.py
grayskull/strategy/abstract_strategy.py
grayskull/strategy/config.yaml
grayskull/strategy/cran.py
grayskull/strategy/parse_poetry_version.py
grayskull/strategy/py_base.py
grayskull/strategy/py_toml.py
grayskull/strategy/pypi.py
grayskull-3.1.0.dist-info/licenses/AUTHORS
grayskull-3.1.0.dist-info/licenses/LICENSE
grayskull-3.1.0.dist-info/METADATA
grayskull-3.1.0.dist-info/WHEEL
grayskull-3.1.0.dist-info/entry_points.txt
grayskull-3.1.0.dist-info/top_level.txt
grayskull-3.1.0.dist-info/RECORD
