Metadata-Version: 2.4
Name: grayskull
Version: 3.1.0
Summary: Project to generate recipes for conda packages
Author-email: Marcelo Duarte Trevisani <marceloduartetrevisani@gmail.com>
License: Apache-2.0
Project-URL: Source, https://github.com/conda/grayskull
Keywords: conda
Requires-Python: >=3.10
License-File: LICENSE
License-File: AUTHORS
Requires-Dist: beautifulsoup4
Requires-Dist: colorama
Requires-Dist: conda-souschef>=3.0.1
Requires-Dist: packaging>=21.3
Requires-Dist: pip
Requires-Dist: pkginfo
Requires-Dist: progressbar2>=3.53.0
Requires-Dist: rapidfuzz>=3.0.0
Requires-Dist: requests
Requires-Dist: ruamel.yaml>=0.16.10
Requires-Dist: ruamel.yaml.jinja2
Requires-Dist: setuptools>=30.3.0
Requires-Dist: stdlib-list
Requires-Dist: tomli; python_version < "3.11"
Requires-Dist: tomli-w
Provides-Extra: testing
Requires-Dist: mock; extra == "testing"
Requires-Dist: pytest; extra == "testing"
Requires-Dist: pytest-console-scripts; extra == "testing"
Requires-Dist: pytest-cov; extra == "testing"
Requires-Dist: pytest-mock; extra == "testing"
Requires-Dist: setuptools-scm; extra == "testing"
Requires-Dist: numpy; extra == "testing"
Provides-Extra: docs
Requires-Dist: furo; extra == "docs"
Requires-Dist: sphinx; extra == "docs"
Requires-Dist: sphinx-argparse; extra == "docs"
Requires-Dist: myst-parser; extra == "docs"
Requires-Dist: mdit-py-plugins>=0.3.0; extra == "docs"
Dynamic: license-file
